autobmt/__init__.py
autobmt/auto_build_scorecard.py
autobmt/auto_build_tree_model.py
autobmt/auto_build_tree_model_lgb.py
autobmt/bayes_opt_tuner.py
autobmt/category_label_encoder.py
autobmt/category_woe_encoder.py
autobmt/detector.py
autobmt/feature_binning.py
autobmt/feature_selection.py
autobmt/logger_utils.py
autobmt/metrics.py
autobmt/plot.py
autobmt/report2excel.py
autobmt/scorecard.py
autobmt/statistics.py
autobmt/stepwise.py
autobmt/transformer.py
autobmt/utils.py
autobmt-0.2.0.dist-info/LICENSE
autobmt-0.2.0.dist-info/METADATA
autobmt-0.2.0.dist-info/WHEEL
autobmt-0.2.0.dist-info/top_level.txt
autobmt-0.2.0.dist-info/RECORD
