Metadata-Version: 2.1
Name: autobmt
Version: 0.2.0
Summary: a modeling tool that automatically builds scorecards and tree models.
Home-page: https://github.com/ZhengRyan/autobmt
Author: RyanZheng
Author-email: zhengruiping000@163.com
License: MIT license
Keywords: autobmt
Platform: UNKNOWN
Classifier: Development Status :: 2 - Pre-Alpha
Classifier: Intended Audience :: Developers
Classifier: License :: OSI Approved :: MIT License
Classifier: Natural Language :: English
Classifier: Programming Language :: Python :: 3
Classifier: Programming Language :: Python :: 3.6
Classifier: Programming Language :: Python :: 3.7
Classifier: Programming Language :: Python :: 3.8
Requires-Python: >=3.6
Requires-Dist: pandas
Requires-Dist: scikit-learn (>=0.21)
Requires-Dist: statsmodels (>=0.11.1)
Requires-Dist: XlsxWriter (>=1.3.7)
Requires-Dist: matplotlib (>=3.1.2)
Requires-Dist: openpyxl (>=3.0.7)
Requires-Dist: bayesian-optimization (==1.1.0)
Requires-Dist: shap (>=0.40.0)
Requires-Dist: joblib (>=0.12)
Requires-Dist: xgboost (<=1.5.0,>=1.2.0)
Requires-Dist: lightgbm (>=3.1.0)
Requires-Dist: seaborn (>=0.10.0)
